lmfetch/__init__.py
lmfetch/builder.py
lmfetch/cache.py
lmfetch/cli.py
lmfetch/mcp_server.py
lmfetch/tokens.py
lmfetch/utils.py
lmfetch-0.3.6.dist-info/licenses/LICENSE
lmfetch-0.3.6.dist-info/METADATA
lmfetch-0.3.6.dist-info/WHEEL
lmfetch-0.3.6.dist-info/entry_points.txt
lmfetch-0.3.6.dist-info/top_level.txt
lmfetch-0.3.6.dist-info/RECORD
