Metadata-Version: 2.4
Name: lmfetch
Version: 0.3.6
Summary: Build intelligent context from codebases and URLs for LLMs
Author-email: Abdulmumin Yaqeen <abdulmuminyqn@gmail.com>
Project-URL: Homepage, https://github.com/Abdulmumin1/lmfetch
Project-URL: Repository, https://github.com/Abdulmumin1/lmfetch
Requires-Python: >=3.13
License-File: LICENSE
Requires-Dist: ai-query
Requires-Dist: aiofiles
Requires-Dist: tiktoken
Requires-Dist: click
Requires-Dist: rich
Requires-Dist: fastmcp>=2.14.3
Provides-Extra: dev
Requires-Dist: pytest; extra == "dev"
Requires-Dist: pytest-asyncio; extra == "dev"
Dynamic: license-file
